sjlogging/__init__.py
sjlogging/handler.py
sjlogging/logger.py
sjlogging/setter.py
sjlogging-0.5.4.dist-info/LICENSE.txt
sjlogging-0.5.4.dist-info/METADATA
sjlogging-0.5.4.dist-info/WHEEL
sjlogging-0.5.4.dist-info/RECORD
